pyfian/.DS_Store
pyfian/__init__.py
pyfian/corporate_finance/__init__.py
pyfian/data/__init__.py
pyfian/derivatives/__init__.py
pyfian/financial_statements/__init__.py
pyfian/portfolio/__init__.py
pyfian/risk_management/__init__.py
pyfian/statistics/__init__.py
pyfian/time_value/.DS_Store
pyfian/time_value/__init__.py
pyfian/time_value/continuous_compounding.py
pyfian/time_value/future_value.py
pyfian/time_value/irr.py
pyfian/time_value/means.py
pyfian/time_value/mortgage.py
pyfian/time_value/present_value.py
pyfian/time_value/real_rates.py
pyfian/utils/__init__.py
pyfian-0.1.0.dist-info/LICENSE
pyfian-0.1.0.dist-info/METADATA
pyfian-0.1.0.dist-info/WHEEL
pyfian-0.1.0.dist-info/RECORD
