Metadata-Version: 2.3
Name: pyfian
Version: 0.1.0
Summary: Package for Python Financial Analyst
Author: Pablo Orazi
Author-email: pabloorazi@gmail.com
Requires-Python: >=3.11,<4.0
Classifier: Programming Language :: Python :: 3
Classifier: Programming Language :: Python :: 3.11
Classifier: Programming Language :: Python :: 3.12
Classifier: Programming Language :: Python :: 3.13
Requires-Dist: matplotlib (>=3.10.3,<4.0.0)
Requires-Dist: numpy (>=2.3.1,<3.0.0)
Requires-Dist: numpy-financial (>=1.0.0,<2.0.0)
Requires-Dist: pandas (>=2.3.0,<3.0.0)
